{"customers":[{"gender":"male","name":{"title":"Mr","first":"Daniel","last":"Kristensen"},"location":{"street":{"number":6257,"name":"Tulipanvej"},"city":"Nimtofte","state":"Nordjylland","country":"Denmark","postcode":20136,"coordinates":{"latitude":"-27.0607","longitude":"-109.8520"},"timezone":{"offset":"+2:00","description":"Kaliningrad, South Africa"}},"email":"daniel.kristensen@example.com","login":{"uuid":"368ae891-9cd9-4401-a843-00aa2c74eeb2","username":"crazydog144","password":"kevin","salt":"JV3Lrcfz","md5":"2d141687e7cf915d81f2a1075a75fbe0","sha1":"5bf47b0fe1731e65ff0883e83d565e23ca582cd7","sha256":"759d838258ee552f8c3a1f4440e58125a975397bcced68c4650686576e7942d6"},"dob":{"date":"1945-09-22T17:10:01.760Z","age":75},"registered":{"date":"2014-03-01T07:12:54.479Z","age":6},"phone":"17438871","cell":"95085030","id":{"name":"CPR","value":"220945-3535"},"picture":{"large":"https://randomuser.me/api/portraits/men/67.jpg","medium":"https://randomuser.me/api/portraits/med/men/67.jpg","thumbnail":"https://randomuser.me/api/portraits/thumb/men/67.jpg"},"nat":"DK"},{"gender":"female","name":{"title":"Miss","first":"Filippa","last":"Christiansen"},"location":{"street":{"number":9388,"name":"Lergravsvej"},"city":"Brøndby Strand","state":"Danmark","country":"Denmark","postcode":11114,"coordinates":{"latitude":"72.7170","longitude":"15.9309"},"timezone":{"offset":"-11:00","description":"Midway Island, Samoa"}},"email":"filippa.christiansen@example.com","login":{"uuid":"1d815059-595a-4413-9f72-00c525215dbb","username":"sadostrich844","password":"qiao","salt":"YxixkhwY","md5":"3544c6a05a7dbac5ee9d8738630ed504","sha1":"7deb7873e127dd337613de0ef7eb89f0abb30e3c","sha256":"8ff9533629b938128512702ca7022d9b625eedcff50d2fbbc339c95cf286904c"},"dob":{"date":"1978-03-04T03:18:28.194Z","age":42},"registered":{"date":"2014-07-27T06:59:53.222Z","age":6},"phone":"50904896","cell":"92064295","id":{"name":"CPR","value":"040378-7276"},"picture":{"large":"https://randomuser.me/api/portraits/women/78.jpg","medium":"https://randomuser.me/api/portraits/med/women/78.jpg","thumbnail":"https://randomuser.me/api/portraits/thumb/women/78.jpg"},"nat":"DK"},{"gender":"female","name":{"title":"Ms","first":"سارینا","last":"رضایی"},"location":{"street":{"number":2178,"name":"شهید ثانی"},"city":"زنجان","state":"هرمزگان","country":"Iran","postcode":17490,"coordinates":{"latitude":"32.8038","longitude":"117.9372"},"timezone":{"offset":"+6:00","description":"Almaty, Dhaka, Colombo"}},"email":"sryn.rdyy@example.com","login":{"uuid":"9bd90f06-dfae-4309-a3e9-c4caac72bc36","username":"bluepanda739","password":"uuuuuu","salt":"w9rU5l4D","md5":"b1da0bb20a89c94b281de089b76bcd80","sha1":"fd1fe47bfebb83b07087634741cd30ce1231bcbc","sha256":"aecb180ab28e4e180bc34dab09f5871872ac5e9c222af76e2821d0e1e2dcddad"},"dob":{"date":"1960-09-21T09:58:31.146Z","age":60},"registered":{"date":"2008-12-18T17:58:24.167Z","age":12},"phone":"060-51207473","cell":"0967-757-5665","id":{"name":"","value":null},"picture":{"large":"https://randomuser.me/api/portraits/women/50.jpg","medium":"https://randomuser.me/api/portraits/med/women/50.jpg","thumbnail":"https://randomuser.me/api/portraits/thumb/women/50.jpg"},"nat":"IR"},{"gender":"female","name":{"title":"Miss","first":"Leah","last":"Walker"},"location":{"street":{"number":1725,"name":"Jones Road"},"city":"Wexford","state":"Clare","country":"Ireland","postcode":68240,"coordinates":{"latitude":"-5.9645","longitude":"75.2482"},"timezone":{"offset":"+1:00","description":"Brussels, Copenhagen, Madrid, Paris"}},"email":"leah.walker@example.com","login":{"uuid":"15f4ce3e-7e3b-4b46-8a19-230b7c49bb8b","username":"blackdog709","password":"fire","salt":"ueJXijhl","md5":"6e22e5505aae617ab40e87a31228bdd7","sha1":"f5d2fb5556b4ffe417392e3a0cfee69e120fe2c3","sha256":"71b63007ba2779327faee5d0e27d6ac80be06b0647de4c59efed9eed1fff2c37"},"dob":{"date":"1993-05-25T16:50:07.188Z","age":27},"registered":{"date":"2003-06-08T00:50:59.362Z","age":17},"phone":"011-864-7709","cell":"081-933-1293","id":{"name":"PPS","value":"5843550T"},"picture":{"large":"https://randomuser.me/api/portraits/women/32.jpg","medium":"https://randomuser.me/api/portraits/med/women/32.jpg","thumbnail":"https://randomuser.me/api/portraits/thumb/women/32.jpg"},"nat":"IE"},{"gender":"male","name":{"title":"Mr","first":"Adem","last":"Çatalbaş"},"location":{"street":{"number":574,"name":"Vatan Cd"},"city":"Tunceli","state":"Ardahan","country":"Turkey","postcode":50893,"coordinates":{"latitude":"7.8910","longitude":"40.8680"},"timezone":{"offset":"-10:00","description":"Hawaii"}},"email":"adem.catalbas@example.com","login":{"uuid":"a9af9e37-25f1-4a51-9c22-13522ae151e9","username":"redgorilla359","password":"thor","salt":"ajamG2vm","md5":"4a984cda39ca918ad209bfcd6bc8a962","sha1":"bf92f6a949fdcf09d2f5af8401fdede45feefa09","sha256":"d0e91d41160fc3a0c9b21fbfb3266b833286d55b751ec2e0468aceb0dd6e8757"},"dob":{"date":"1977-11-26T20:16:53.238Z","age":43},"registered":{"date":"2016-05-13T14:29:02.075Z","age":4},"phone":"(647)-640-5665","cell":"(704)-603-1337","id":{"name":"","value":null},"picture":{"large":"https://randomuser.me/api/portraits/men/22.jpg","medium":"https://randomuser.me/api/portraits/med/men/22.jpg","thumbnail":"https://randomuser.me/api/portraits/thumb/men/22.jpg"},"nat":"TR"},{"gender":"female","name":{"title":"Ms","first":"Olivia","last":"Holt"},"location":{"street":{"number":7058,"name":"O'Connell Street"},"city":"Oranmore","state":"Fingal","country":"Ireland","postcode":59745,"coordinates":{"latitude":"-6.3050","longitude":"85.3895"},"timezone":{"offset":"+2:00","description":"Kaliningrad, South Africa"}},"email":"olivia.holt@example.com","login":{"uuid":"b0fe6624-f68d-4758-91e3-1e10fce70203","username":"brownduck101","password":"trans","salt":"luRcPomD","md5":"50464621ed7ac5f691e1260891656469","sha1":"b6c2e5bc96af7e29b290305fdd743f9b431bc2c5","sha256":"436d868de14561a2f1bc79e3805b7a104029662f4057dadc61c5f30063fee086"},"dob":{"date":"1945-02-07T02:28:57.304Z","age":75},"registered":{"date":"2006-03-26T20:29:44.973Z","age":14},"phone":"071-520-9080","cell":"081-836-8246","id":{"name":"PPS","value":"4800507T"},"picture":{"large":"https://randomuser.me/api/portraits/women/93.jpg","medium":"https://randomuser.me/api/portraits/med/women/93.jpg","thumbnail":"https://randomuser.me/api/portraits/thumb/women/93.jpg"},"nat":"IE"},{"gender":"male","name":{"title":"Mr","first":"Baptiste","last":"Marchand"},"location":{"street":{"number":6621,"name":"Rue Louis-Blanqui"},"city":"Saint-Pierre","state":"Seine-Saint-Denis","country":"France","postcode":82421,"coordinates":{"latitude":"4.5884","longitude":"132.2668"},"timezone":{"offset":"+4:30","description":"Kabul"}},"email":"baptiste.marchand@example.com","login":{"uuid":"53ea649c-3a7b-4961-9aa8-b06a14266bae","username":"silverbear104","password":"civicsi","salt":"riJJyphi","md5":"e8f126b03b755571c8efa83362117f9a","sha1":"3dd24d5008e8a9eb734c0def962e62c37a8f65c8","sha256":"3b68e171e7da25ee26000f411d100f6f759bd3a695958453745751c445f2d2f6"},"dob":{"date":"1972-01-08T23:54:15.203Z","age":48},"registered":{"date":"2010-07-18T00:18:52.083Z","age":10},"phone":"04-44-39-61-78","cell":"06-54-73-72-14","id":{"name":"INSEE","value":"1NNaN44690351 25"},"picture":{"large":"https://randomuser.me/api/portraits/men/51.jpg","medium":"https://randomuser.me/api/portraits/med/men/51.jpg","thumbnail":"https://randomuser.me/api/portraits/thumb/men/51.jpg"},"nat":"FR"},{"gender":"female","name":{"title":"Miss","first":"Cassandra","last":"Duval"},"location":{"street":{"number":6202,"name":"Avenue Vauban"},"city":"Mulhouse","state":"Doubs","country":"France","postcode":29810,"coordinates":{"latitude":"46.9096","longitude":"-28.0482"},"timezone":{"offset":"-11:00","description":"Midway Island, Samoa"}},"email":"cassandra.duval@example.com","login":{"uuid":"c8b8b482-5b0a-4337-a330-03fd930f0d1d","username":"smalllion432","password":"facial","salt":"2ZLvCxI1","md5":"f028b6c687630ddea6254be1edd0922f","sha1":"d606bd133d1b0a02da1c4d5395c4a1e9549171c2","sha256":"44b1711f02c373594f35e979e0ca6a1c8cdc403a1b222551885d58237de1b273"},"dob":{"date":"1961-02-11T17:48:31.400Z","age":59},"registered":{"date":"2013-02-01T05:29:28.872Z","age":7},"phone":"05-02-71-98-19","cell":"06-46-32-33-09","id":{"name":"INSEE","value":"2NNaN33150609 85"},"picture":{"large":"https://randomuser.me/api/portraits/women/0.jpg","medium":"https://randomuser.me/api/portraits/med/women/0.jpg","thumbnail":"https://randomuser.me/api/portraits/thumb/women/0.jpg"},"nat":"FR"},{"gender":"male","name":{"title":"Mr","first":"Hauke","last":"Zobel"},"location":{"street":{"number":2283,"name":"Bachstraße"},"city":"Anhalt-Bitterfeld","state":"Mecklenburg-Vorpommern","country":"Germany","postcode":61028,"coordinates":{"latitude":"-20.5741","longitude":"62.0613"},"timezone":{"offset":"-9:00","description":"Alaska"}},"email":"hauke.zobel@example.com","login":{"uuid":"d47a7e10-80c8-4419-aaed-dc429963123c","username":"heavyrabbit782","password":"shuai","salt":"P8yZCOpl","md5":"74d0bbb5a19251ac159adf5983a0a5c6","sha1":"59d6eca85a3fb56b2a986194f9c8dc56edf6eb30","sha256":"f45044e21fe6c0c7b19a71a55901566a886a53c0a8e684f8e46b59500befd9e5"},"dob":{"date":"1948-11-21T23:20:48.464Z","age":72},"registered":{"date":"2006-11-10T05:19:37.583Z","age":14},"phone":"0588-5932642","cell":"0178-6225678","id":{"name":"","value":null},"picture":{"large":"https://randomuser.me/api/portraits/men/79.jpg","medium":"https://randomuser.me/api/portraits/med/men/79.jpg","thumbnail":"https://randomuser.me/api/portraits/thumb/men/79.jpg"},"nat":"DE"},{"gender":"female","name":{"title":"Miss","first":"Suzanna","last":"Hunter"},"location":{"street":{"number":907,"name":"Green Lane"},"city":"Lisburn","state":"Lancashire","country":"United Kingdom","postcode":"UA17 0EB","coordinates":{"latitude":"-86.9182","longitude":"-178.3095"},"timezone":{"offset":"-2:00","description":"Mid-Atlantic"}},"email":"suzanna.hunter@example.com","login":{"uuid":"878b675f-b2cd-487b-9b43-6779e15824b7","username":"sadswan291","password":"rocky","salt":"7FQTUCsD","md5":"13ea6fc0d812d91c07a6cffd189bdb76","sha1":"afe829357a2491963c90188e765527b902590cde","sha256":"5a8c5e40b5a7fd061531f05053f1af2773d333db546be41d671def65d70d761d"},"dob":{"date":"1952-05-12T12:33:20.547Z","age":68},"registered":{"date":"2011-10-10T21:51:46.158Z","age":9},"phone":"017684 25192","cell":"0777-628-501","id":{"name":"NINO","value":"ZG 46 22 14 A"},"picture":{"large":"https://randomuser.me/api/portraits/women/83.jpg","medium":"https://randomuser.me/api/portraits/med/women/83.jpg","thumbnail":"https://randomuser.me/api/portraits/thumb/women/83.jpg"},"nat":"GB"},{"gender":"male","name":{"title":"Mr","first":"Nicklas","last":"Møller"},"location":{"street":{"number":2166,"name":"Frueløkke"},"city":"Århus C.","state":"Danmark","country":"Denmark","postcode":22445,"coordinates":{"latitude":"53.3982","longitude":"-121.5444"},"timezone":{"offset":"+5:45","description":"Kathmandu"}},"email":"nicklas.moller@example.com","login":{"uuid":"44092843-dd95-4758-95d8-5490f03c2ee2","username":"redmouse373","password":"paladin","salt":"OT2nnMhw","md5":"611459583f0b246b46c6e632a7d69b65","sha1":"a1468dbd1b40f06b589d065868bb67d6428816f8","sha256":"bbf99633452146ac9b84b1e1fd5034f1a7a9bad67e1b7b67e176fa040758bc43"},"dob":{"date":"1945-02-26T09:18:16.468Z","age":75},"registered":{"date":"2016-12-13T16:09:45.162Z","age":4},"phone":"93269774","cell":"33037243","id":{"name":"CPR","value":"260245-6841"},"picture":{"large":"https://randomuser.me/api/portraits/men/93.jpg","medium":"https://randomuser.me/api/portraits/med/men/93.jpg","thumbnail":"https://randomuser.me/api/portraits/thumb/men/93.jpg"},"nat":"DK"},{"gender":"female","name":{"title":"Mademoiselle","first":"Marinette","last":"Bertrand"},"location":{"street":{"number":2140,"name":"Quai Charles-De-Gaulle"},"city":"Mutrux","state":"Graubünden","country":"Switzerland","postcode":2222,"coordinates":{"latitude":"77.4391","longitude":"-31.9821"},"timezone":{"offset":"+4:30","description":"Kabul"}},"email":"marinette.bertrand@example.com","login":{"uuid":"964450f5-5291-4a0f-9a35-6f130079af6d","username":"smallleopard251","password":"choice","salt":"B2s9VMW0","md5":"f454a2f560f70bbad7d0831c0298b4f6","sha1":"2f07edc059d36cdd326aee9a9446d24bc5b381be","sha256":"3e89e49982e2dae20ad85777a96bc32e165f56fffaf015a11ff8bb4d7c77a873"},"dob":{"date":"1976-09-26T22:27:01.881Z","age":44},"registered":{"date":"2004-05-07T06:46:20.221Z","age":16},"phone":"076 090 97 30","cell":"077 518 35 08","id":{"name":"AVS","value":"756.6491.3120.02"},"picture":{"large":"https://randomuser.me/api/portraits/women/41.jpg","medium":"https://randomuser.me/api/portraits/med/women/41.jpg","thumbnail":"https://randomuser.me/api/portraits/thumb/women/41.jpg"},"nat":"CH"},{"gender":"male","name":{"title":"Mr","first":"Konsta","last":"Wirta"},"location":{"street":{"number":1340,"name":"Pyynikintie"},"city":"Pöytyä","state":"Tavastia Proper","country":"Finland","postcode":83795,"coordinates":{"latitude":"-6.1779","longitude":"55.3903"},"timezone":{"offset":"-8:00","description":"Pacific Time (US & Canada)"}},"email":"konsta.wirta@example.com","login":{"uuid":"32c7cc14-c9ee-48f5-8b73-da448abd9ae7","username":"angrybutterfly857","password":"lily","salt":"SoqjXweV","md5":"4bc6e6ec3ef2ee553b6ae9f7268a7658","sha1":"b2c25483919ba0529fd13bd55cae346ba86e0a5b","sha256":"cd415912ba2000532a31b5411160d1869a7f375cdcfbbbbe65f95a81046e40e9"},"dob":{"date":"1974-03-30T10:49:14.199Z","age":46},"registered":{"date":"2017-11-18T12:50:21.768Z","age":3},"phone":"09-265-121","cell":"047-917-68-85","id":{"name":"HETU","value":"NaNNA967undefined"},"picture":{"large":"https://randomuser.me/api/portraits/men/54.jpg","medium":"https://randomuser.me/api/portraits/med/men/54.jpg","thumbnail":"https://randomuser.me/api/portraits/thumb/men/54.jpg"},"nat":"FI"},{"gender":"female","name":{"title":"Mrs","first":"Serine","last":"Sulen"},"location":{"street":{"number":2794,"name":"Sisikveien"},"city":"Figgjo","state":"Oslo","country":"Norway","postcode":"4346","coordinates":{"latitude":"-33.5168","longitude":"-43.9586"},"timezone":{"offset":"+7:00","description":"Bangkok, Hanoi, Jakarta"}},"email":"serine.sulen@example.com","login":{"uuid":"1379bf8b-bb74-47cb-9328-d04499c990cf","username":"ticklishsnake618","password":"julian","salt":"YOjsZQpH","md5":"c7f8eb406a62a8b91aadbcae2fbe98c6","sha1":"e96d99ec46a13323488c927f9d748f5751a49b51","sha256":"70a78251b2a14aa83751ed96644af21cda6b9472a12adb8d1910f661426a1356"},"dob":{"date":"1960-11-01T19:18:12.156Z","age":60},"registered":{"date":"2007-12-27T18:59:42.943Z","age":13},"phone":"81060121","cell":"43901069","id":{"name":"FN","value":"01116019856"},"picture":{"large":"https://randomuser.me/api/portraits/women/81.jpg","medium":"https://randomuser.me/api/portraits/med/women/81.jpg","thumbnail":"https://randomuser.me/api/portraits/thumb/women/81.jpg"},"nat":"NO"},{"gender":"female","name":{"title":"Mrs","first":"Camila","last":"Cooper"},"location":{"street":{"number":8391,"name":"Hunters Creek Dr"},"city":"Fort Lauderdale","state":"Hawaii","country":"United States","postcode":99364,"coordinates":{"latitude":"75.1653","longitude":"-58.7012"},"timezone":{"offset":"+3:00","description":"Baghdad, Riyadh, Moscow, St. Petersburg"}},"email":"camila.cooper@example.com","login":{"uuid":"4f820aca-012c-4116-a2d1-893f424381c5","username":"redkoala118","password":"hahahaha","salt":"cu1bJm0r","md5":"4b32c8e6f79b32439da4e74c703ad491","sha1":"e1ee49df642c4792df1762bc084fb76e29e9abbc","sha256":"38f59a25125bd62f3e12112884edc3cd7f68b0849daab397b00d04821b175154"},"dob":{"date":"1974-01-18T14:29:39.585Z","age":46},"registered":{"date":"2008-10-14T03:33:06.120Z","age":12},"phone":"(200)-840-2465","cell":"(345)-339-7556","id":{"name":"SSN","value":"647-69-9200"},"picture":{"large":"https://randomuser.me/api/portraits/women/87.jpg","medium":"https://randomuser.me/api/portraits/med/women/87.jpg","thumbnail":"https://randomuser.me/api/portraits/thumb/women/87.jpg"},"nat":"US"},{"gender":"female","name":{"title":"Miss","first":"Ella","last":"Miles"},"location":{"street":{"number":6631,"name":"Fairview Road"},"city":"Sheffield","state":"West Midlands","country":"United Kingdom","postcode":"YA4 9TT","coordinates":{"latitude":"-71.9675","longitude":"-163.8604"},"timezone":{"offset":"-7:00","description":"Mountain Time (US & Canada)"}},"email":"ella.miles@example.com","login":{"uuid":"7fe32eda-b5c9-4848-8dd5-d361225a3985","username":"orangegoose120","password":"welcome","salt":"u6fpQI2N","md5":"914c8be516d6af7488978673f0b12466","sha1":"e7767b7c774ed0b1c64f7f2cc89e08ec0083a978","sha256":"cecf199e0478254bb1834a83d7ce3d4df475473e7806ba8f414a32e67b3bce0f"},"dob":{"date":"1993-12-02T09:34:21.401Z","age":27},"registered":{"date":"2006-11-07T00:16:58.411Z","age":14},"phone":"015396 15270","cell":"0765-177-227","id":{"name":"NINO","value":"YM 58 58 70 K"},"picture":{"large":"https://randomuser.me/api/portraits/women/52.jpg","medium":"https://randomuser.me/api/portraits/med/women/52.jpg","thumbnail":"https://randomuser.me/api/portraits/thumb/women/52.jpg"},"nat":"GB"},{"gender":"male","name":{"title":"Mr","first":"Elijah","last":"Wright"},"location":{"street":{"number":702,"name":"Symonds Street"},"city":"Timaru","state":"Tasman","country":"New Zealand","postcode":57132,"coordinates":{"latitude":"-18.2492","longitude":"-28.9202"},"timezone":{"offset":"+9:00","description":"Tokyo, Seoul, Osaka, Sapporo, Yakutsk"}},"email":"elijah.wright@example.com","login":{"uuid":"8662de38-2f3b-4fd9-ac32-9f03a2c131dd","username":"bigelephant420","password":"mathew","salt":"O0PthqqV","md5":"10b8f3f77e80c7a231a3d06982306fb2","sha1":"912aaa879248f964dc80530c061198304da5f95a","sha256":"a94c3b3fdb678f9576e2c6353724d7e6b5d9e0d3266184b71a80e863e86a2923"},"dob":{"date":"1960-05-24T04:20:08.395Z","age":60},"registered":{"date":"2003-08-16T16:38:32.913Z","age":17},"phone":"(008)-315-9811","cell":"(390)-026-7536","id":{"name":"","value":null},"picture":{"large":"https://randomuser.me/api/portraits/men/77.jpg","medium":"https://randomuser.me/api/portraits/med/men/77.jpg","thumbnail":"https://randomuser.me/api/portraits/thumb/men/77.jpg"},"nat":"NZ"},{"gender":"female","name":{"title":"Ms","first":"Gabrielle","last":"Dupuis"},"location":{"street":{"number":2575,"name":"Boulevard de la Duchère"},"city":"Dijon","state":"Savoie","country":"France","postcode":87610,"coordinates":{"latitude":"46.0807","longitude":"81.5611"},"timezone":{"offset":"-10:00","description":"Hawaii"}},"email":"gabrielle.dupuis@example.com","login":{"uuid":"93e81113-60e6-4fff-bf9b-3f66c02c1215","username":"tinymouse239","password":"duffy","salt":"bhzZNg6l","md5":"593ebabe4023836715097e40c94c56ba","sha1":"d7127789b8d9f11723cd11dc4248ba7a8593c8d6","sha256":"93dfbd89d3a1024d4d7243210a93a6e29b20b4664c76c1b5fde29f9d5153851d"},"dob":{"date":"1965-03-27T23:22:59.572Z","age":55},"registered":{"date":"2018-03-22T22:58:57.563Z","age":2},"phone":"05-29-21-91-82","cell":"06-82-98-25-28","id":{"name":"INSEE","value":"2NNaN99391757 81"},"picture":{"large":"https://randomuser.me/api/portraits/women/66.jpg","medium":"https://randomuser.me/api/portraits/med/women/66.jpg","thumbnail":"https://randomuser.me/api/portraits/thumb/women/66.jpg"},"nat":"FR"},{"gender":"female","name":{"title":"Ms","first":"Clara","last":"Olsen"},"location":{"street":{"number":7069,"name":"Damvej"},"city":"Sundby/Erslev","state":"Syddanmark","country":"Denmark","postcode":50304,"coordinates":{"latitude":"35.6499","longitude":"-163.6135"},"timezone":{"offset":"-1:00","description":"Azores, Cape Verde Islands"}},"email":"clara.olsen@example.com","login":{"uuid":"07345342-098f-4379-b427-055a8b33f02a","username":"bluecat100","password":"tribble","salt":"akoobMe7","md5":"e80fcde872ed203ffa3eaca925d70921","sha1":"b376d23dd9a15665a9a0f2ef773d3fdf04d46961","sha256":"45bdc5289b146ad9d220c3f8188221dc9d3f4bef4ee685fe4aaed7907c43f332"},"dob":{"date":"1967-02-01T17:37:20.399Z","age":53},"registered":{"date":"2015-12-07T22:27:12.959Z","age":5},"phone":"01746698","cell":"78133454","id":{"name":"CPR","value":"010267-6145"},"picture":{"large":"https://randomuser.me/api/portraits/women/33.jpg","medium":"https://randomuser.me/api/portraits/med/women/33.jpg","thumbnail":"https://randomuser.me/api/portraits/thumb/women/33.jpg"},"nat":"DK"},{"gender":"female","name":{"title":"Miss","first":"Patricia","last":"Payne"},"location":{"street":{"number":9720,"name":"Church Lane"},"city":"Cork","state":"Longford","country":"Ireland","postcode":84519,"coordinates":{"latitude":"41.9049","longitude":"127.7722"},"timezone":{"offset":"-4:00","description":"Atlantic Time (Canada), Caracas, La Paz"}},"email":"patricia.payne@example.com","login":{"uuid":"33925aaa-40df-4f53-bfcb-76506b466ad7","username":"orangegorilla582","password":"retard","salt":"3KhzgGJx","md5":"3d3a01c471ccae5e98a8f37d12468cbb","sha1":"423b080105db5a1af59bd85548c3502470e6ec62","sha256":"ed760bbacce9814bab25c4d74e7b33bb904de998afa5a9a942bded275c843014"},"dob":{"date":"1960-10-23T16:40:09.565Z","age":60},"registered":{"date":"2017-03-03T12:03:58.210Z","age":3},"phone":"031-073-3919","cell":"081-778-1425","id":{"name":"PPS","value":"5500814T"},"picture":{"large":"https://randomuser.me/api/portraits/women/75.jpg","medium":"https://randomuser.me/api/portraits/med/women/75.jpg","thumbnail":"https://randomuser.me/api/portraits/thumb/women/75.jpg"},"nat":"IE"},{"gender":"female","name":{"title":"Ms","first":"Isabella","last":"Jørgensen"},"location":{"street":{"number":7330,"name":"Jupitervej"},"city":"Hurup Thy","state":"Sjælland","country":"Denmark","postcode":17985,"coordinates":{"latitude":"-69.3143","longitude":"-97.0631"},"timezone":{"offset":"+3:00","description":"Baghdad, Riyadh, Moscow, St. Petersburg"}},"email":"isabella.jorgensen@example.com","login":{"uuid":"8a04a359-517d-44fc-9cf3-c829164231f0","username":"tinybird207","password":"mikey","salt":"LlMe5NJ1","md5":"9fe2645f99cfb5b693fdac81949059a6","sha1":"74d6c19b9b2e5a0147b3ba450d8814cb01c6fee2","sha256":"d6d834538014e523e4618fd583cbd3f73016afce9cb0876630c0dc17fa32fd9d"},"dob":{"date":"1971-02-25T09:43:32.196Z","age":49},"registered":{"date":"2018-09-18T01:02:42.092Z","age":2},"phone":"55487638","cell":"34816219","id":{"name":"CPR","value":"250271-7173"},"picture":{"large":"https://randomuser.me/api/portraits/women/78.jpg","medium":"https://randomuser.me/api/portraits/med/women/78.jpg","thumbnail":"https://randomuser.me/api/portraits/thumb/women/78.jpg"},"nat":"DK"},{"gender":"male","name":{"title":"Mr","first":"Troy","last":"Gonzalez"},"location":{"street":{"number":5578,"name":"E North St"},"city":"Cairns","state":"New South Wales","country":"Australia","postcode":3078,"coordinates":{"latitude":"81.7572","longitude":"99.3996"},"timezone":{"offset":"+4:30","description":"Kabul"}},"email":"troy.gonzalez@example.com","login":{"uuid":"61782d58-0da6-4f26-a300-3707f229bddb","username":"heavypanda293","password":"masterbaiting","salt":"B8NNXZDF","md5":"19693185c82fcdc6f5fbd8567d11dd00","sha1":"a7eb80124c6b32f3d50a7044876ffaff2d6f9cb3","sha256":"0f06c24e1495907531076460cfb4b5d46f914bec62f4801a1280e8c4c88d5e21"},"dob":{"date":"1963-01-18T21:16:01.669Z","age":57},"registered":{"date":"2013-08-24T08:49:01.093Z","age":7},"phone":"02-8131-4653","cell":"0440-602-918","id":{"name":"TFN","value":"849372543"},"picture":{"large":"https://randomuser.me/api/portraits/men/15.jpg","medium":"https://randomuser.me/api/portraits/med/men/15.jpg","thumbnail":"https://randomuser.me/api/portraits/thumb/men/15.jpg"},"nat":"AU"},{"gender":"female","name":{"title":"Mademoiselle","first":"Viviana","last":"Denis"},"location":{"street":{"number":475,"name":"Rue de L'Abbé-Rousselot"},"city":"Lavigny","state":"Neuchâtel","country":"Switzerland","postcode":3361,"coordinates":{"latitude":"-47.2778","longitude":"-86.0126"},"timezone":{"offset":"+1:00","description":"Brussels, Copenhagen, Madrid, Paris"}},"email":"viviana.denis@example.com","login":{"uuid":"2c51c801-d8e8-4e39-8341-be2c9de8eacc","username":"silverpeacock505","password":"room","salt":"QitTTDtt","md5":"6d99bc07bf65919153d2bb92c5f2929c","sha1":"d7904038af00ab56999cd448a641d7089415f13f","sha256":"38a90b36d4dc92b84ce4a69bb54847cb34a0ad1b8c26a52d878b9bec8fbb8ee8"},"dob":{"date":"1978-06-16T22:37:03.021Z","age":42},"registered":{"date":"2016-07-08T20:55:25.248Z","age":4},"phone":"077 309 67 21","cell":"078 735 20 86","id":{"name":"AVS","value":"756.3906.6393.40"},"picture":{"large":"https://randomuser.me/api/portraits/women/72.jpg","medium":"https://randomuser.me/api/portraits/med/women/72.jpg","thumbnail":"https://randomuser.me/api/portraits/thumb/women/72.jpg"},"nat":"CH"},{"gender":"male","name":{"title":"Mr","first":"Miguel","last":"Garrido"},"location":{"street":{"number":7332,"name":"Avenida del Planetario"},"city":"Cuenca","state":"Cataluña","country":"Spain","postcode":90120,"coordinates":{"latitude":"88.2763","longitude":"123.2744"},"timezone":{"offset":"-6:00","description":"Central Time (US & Canada), Mexico City"}},"email":"miguel.garrido@example.com","login":{"uuid":"d8c4c29a-da24-4da4-87dd-945df20a0243","username":"bigpeacock636","password":"4121","salt":"CM4bewb6","md5":"60de5b6434e4045549ff82583368ce90","sha1":"1d9e37b3937ee388fe169f9ef5526240af2fa2c0","sha256":"2505e7c11fb06060d65565d7a52735917249c87370ecbc653cc0a3f5e926ea88"},"dob":{"date":"1979-11-23T06:01:11.160Z","age":41},"registered":{"date":"2007-02-02T14:20:04.216Z","age":13},"phone":"908-509-986","cell":"646-344-901","id":{"name":"DNI","value":"77489172-C"},"picture":{"large":"https://randomuser.me/api/portraits/men/24.jpg","medium":"https://randomuser.me/api/portraits/med/men/24.jpg","thumbnail":"https://randomuser.me/api/portraits/thumb/men/24.jpg"},"nat":"ES"},{"gender":"male","name":{"title":"Mr","first":"Délio","last":"Ribeiro"},"location":{"street":{"number":4681,"name":"Rua Maranhão "},"city":"Santana de Parnaíba","state":"Rio Grande do Sul","country":"Brazil","postcode":18686,"coordinates":{"latitude":"-89.2193","longitude":"-37.7414"},"timezone":{"offset":"+5:30","description":"Bombay, Calcutta, Madras, New Delhi"}},"email":"delio.ribeiro@example.com","login":{"uuid":"e0209f97-fa22-4a8d-a53f-05d093f46a60","username":"blueleopard228","password":"tucson","salt":"Q3kN3Lyl","md5":"74e51907bb86a985c945aaca72c7f0ad","sha1":"0be385fdde12c473abc3580e85a3eb8f5a9471a8","sha256":"84ebccf559056fac4be6b2112554af4dcc12b314577ca6f5459c9a3db82d7bad"},"dob":{"date":"1969-07-20T20:05:37.689Z","age":51},"registered":{"date":"2015-04-08T19:56:34.943Z","age":5},"phone":"(49) 5204-6089","cell":"(91) 6408-3420","id":{"name":"","value":null},"picture":{"large":"https://randomuser.me/api/portraits/men/57.jpg","medium":"https://randomuser.me/api/portraits/med/men/57.jpg","thumbnail":"https://randomuser.me/api/portraits/thumb/men/57.jpg"},"nat":"BR"},{"gender":"female","name":{"title":"Ms","first":"Asta","last":"Christensen"},"location":{"street":{"number":8155,"name":"Havrevej"},"city":"Ryslinge","state":"Syddanmark","country":"Denmark","postcode":97133,"coordinates":{"latitude":"7.8186","longitude":"-45.0122"},"timezone":{"offset":"+9:00","description":"Tokyo, Seoul, Osaka, Sapporo, Yakutsk"}},"email":"asta.christensen@example.com","login":{"uuid":"e301d703-7a96-4794-9fb8-8a97baee4018","username":"crazyladybug360","password":"puffy","salt":"brN5ZqKj","md5":"7706ec85856706b95052631b025a0d8f","sha1":"724475458f849e5be63dacd756952c14266b9a17","sha256":"d8fe0612a62e89ce7a121e0a8cfd5b9654da8662091c0a268284baf1b09af91e"},"dob":{"date":"1972-11-18T09:11:07.231Z","age":48},"registered":{"date":"2015-06-17T13:37:34.262Z","age":5},"phone":"27872396","cell":"47544077","id":{"name":"CPR","value":"181172-3184"},"picture":{"large":"https://randomuser.me/api/portraits/women/25.jpg","medium":"https://randomuser.me/api/portraits/med/women/25.jpg","thumbnail":"https://randomuser.me/api/portraits/thumb/women/25.jpg"},"nat":"DK"},{"gender":"female","name":{"title":"Miss","first":"آرمیتا","last":"جعفری"},"location":{"street":{"number":3651,"name":"برادران حسنی"},"city":"بندرعباس","state":"خراسان شمالی","country":"Iran","postcode":32588,"coordinates":{"latitude":"8.1796","longitude":"-64.7477"},"timezone":{"offset":"-5:00","description":"Eastern Time (US & Canada), Bogota, Lima"}},"email":"armyt.jaafry@example.com","login":{"uuid":"913a2ce3-5e14-4a8d-af96-0e4862b340db","username":"lazycat345","password":"babies","salt":"9icbrdd2","md5":"8fb2fc3484b77357e33419c017e0d1c8","sha1":"335b107994c7b00fc5a7e7bc5f1888629cff0f73","sha256":"40083cc4d372eb8489536645dcbc492b8def8db4ad71753d25eb3036e06fe7fd"},"dob":{"date":"1954-09-03T03:38:11.932Z","age":66},"registered":{"date":"2015-01-06T10:41:15.137Z","age":5},"phone":"067-57977082","cell":"0964-932-3822","id":{"name":"","value":null},"picture":{"large":"https://randomuser.me/api/portraits/women/8.jpg","medium":"https://randomuser.me/api/portraits/med/women/8.jpg","thumbnail":"https://randomuser.me/api/portraits/thumb/women/8.jpg"},"nat":"IR"},{"gender":"male","name":{"title":"Mr","first":"Erwan","last":"Berger"},"location":{"street":{"number":8739,"name":"Avenue de la Libération"},"city":"Amiens","state":"Ille-et-Vilaine","country":"France","postcode":64653,"coordinates":{"latitude":"80.2426","longitude":"110.8529"},"timezone":{"offset":"-12:00","description":"Eniwetok, Kwajalein"}},"email":"erwan.berger@example.com","login":{"uuid":"220f1067-0cd0-4cac-b488-3c08286ff20a","username":"bigzebra788","password":"sandrine","salt":"Wi9InV40","md5":"06af419a4c4e0df25476f5ae2a94fcbb","sha1":"7a15d382690c4227d7e556680538582cbe2f5610","sha256":"39ff173eaef94fbb2e5fcea583630a1f725c3df72b19904810f5d868e1a2559c"},"dob":{"date":"1986-10-24T10:14:16.357Z","age":34},"registered":{"date":"2009-08-31T07:05:34.586Z","age":11},"phone":"02-52-12-57-44","cell":"06-79-46-22-91","id":{"name":"INSEE","value":"1NNaN45251615 53"},"picture":{"large":"https://randomuser.me/api/portraits/men/90.jpg","medium":"https://randomuser.me/api/portraits/med/men/90.jpg","thumbnail":"https://randomuser.me/api/portraits/thumb/men/90.jpg"},"nat":"FR"},{"gender":"male","name":{"title":"Mr","first":"Alex","last":"Molina"},"location":{"street":{"number":6433,"name":"Avenida de Burgos"},"city":"Castellón de la Plana","state":"Región de Murcia","country":"Spain","postcode":17723,"coordinates":{"latitude":"33.9319","longitude":"15.4038"},"timezone":{"offset":"-9:00","description":"Alaska"}},"email":"alex.molina@example.com","login":{"uuid":"f2bf6a3a-2eb9-4529-8c08-799007b94d43","username":"bigwolf327","password":"dynasty","salt":"cnMMKG61","md5":"84e352b7999bb9454f5e9703308d29bf","sha1":"5f6da30ddffb44767ed91c6b2a7161c257702c49","sha256":"0c612b06c71feb1b8e769897005a28e550f26ab8d7f73cc1bef51e8ac3e52f57"},"dob":{"date":"1952-01-13T05:33:05.255Z","age":68},"registered":{"date":"2012-09-24T12:16:02.720Z","age":8},"phone":"998-177-061","cell":"600-299-752","id":{"name":"DNI","value":"49286664-V"},"picture":{"large":"https://randomuser.me/api/portraits/men/1.jpg","medium":"https://randomuser.me/api/portraits/med/men/1.jpg","thumbnail":"https://randomuser.me/api/portraits/thumb/men/1.jpg"},"nat":"ES"},{"gender":"male","name":{"title":"Monsieur","first":"Van","last":"Lacroix"},"location":{"street":{"number":6754,"name":"Avenue de L'Abbé-Roussel"},"city":"Nusshof","state":"St. Gallen","country":"Switzerland","postcode":7374,"coordinates":{"latitude":"15.2731","longitude":"-112.6830"},"timezone":{"offset":"-10:00","description":"Hawaii"}},"email":"van.lacroix@example.com","login":{"uuid":"87e446c3-7d81-4f29-84cc-8035398b9fea","username":"angrymouse112","password":"iomega","salt":"aw8Ut58Q","md5":"b05cf7d458a34b1fcd9321622c863b15","sha1":"cadb827ddf105f3624a781baa60b299daaba073d","sha256":"c2c15a73d4cf14af1d8f06df571966c4331d3709b0fd5df883af023aabeb23ea"},"dob":{"date":"1957-03-14T08:32:22.515Z","age":63},"registered":{"date":"2003-02-04T17:33:29.652Z","age":17},"phone":"077 189 68 20","cell":"078 927 04 23","id":{"name":"AVS","value":"756.6863.4192.97"},"picture":{"large":"https://randomuser.me/api/portraits/men/91.jpg","medium":"https://randomuser.me/api/portraits/med/men/91.jpg","thumbnail":"https://randomuser.me/api/portraits/thumb/men/91.jpg"},"nat":"CH"},{"gender":"male","name":{"title":"Mr","first":"Euclides","last":"Rezende"},"location":{"street":{"number":6799,"name":"Rua Duque de Caxias "},"city":"Sobral","state":"Alagoas","country":"Brazil","postcode":86815,"coordinates":{"latitude":"64.6020","longitude":"-102.8310"},"timezone":{"offset":"-5:00","description":"Eastern Time (US & Canada), Bogota, Lima"}},"email":"euclides.rezende@example.com","login":{"uuid":"7a91bc44-cbdb-43cf-87eb-b6bfe89e991a","username":"happyostrich554","password":"bryan1","salt":"bGeDcjVR","md5":"5311ca0f11284742df794873332596c5","sha1":"5c1cc985eb0439e92ec49a0ff5223e814381fe30","sha256":"c9deddfa619c5a026039c42798229a5e982945e7afdf781bbb5dcb0cd42a11c7"},"dob":{"date":"1944-12-26T11:49:58.468Z","age":76},"registered":{"date":"2002-12-30T03:52:27.796Z","age":18},"phone":"(16) 2085-2738","cell":"(38) 6248-3402","id":{"name":"","value":null},"picture":{"large":"https://randomuser.me/api/portraits/men/12.jpg","medium":"https://randomuser.me/api/portraits/med/men/12.jpg","thumbnail":"https://randomuser.me/api/portraits/thumb/men/12.jpg"},"nat":"BR"},{"gender":"female","name":{"title":"Mrs","first":"Rosa","last":"Rasmussen"},"location":{"street":{"number":9298,"name":"Kastanie Alle"},"city":"Agerbæk","state":"Sjælland","country":"Denmark","postcode":55106,"coordinates":{"latitude":"72.5847","longitude":"-57.5564"},"timezone":{"offset":"-12:00","description":"Eniwetok, Kwajalein"}},"email":"rosa.rasmussen@example.com","login":{"uuid":"7f0f3859-67ff-453f-88e8-dc06d05fe1dc","username":"yellowleopard407","password":"010203","salt":"ctoXf7H1","md5":"2fdf18fbf1066c56ae64c728eb25c923","sha1":"cda855873a34b05728c8a61de0f55cfc1d734691","sha256":"b8e957b0e1eaf489037e9f35b98fb249c26b81f1c88ccdce385b01b922ade86a"},"dob":{"date":"1997-09-15T03:17:33.575Z","age":23},"registered":{"date":"2003-12-21T17:40:52.658Z","age":17},"phone":"71492115","cell":"42176418","id":{"name":"CPR","value":"150997-1025"},"picture":{"large":"https://randomuser.me/api/portraits/women/33.jpg","medium":"https://randomuser.me/api/portraits/med/women/33.jpg","thumbnail":"https://randomuser.me/api/portraits/thumb/women/33.jpg"},"nat":"DK"},{"gender":"female","name":{"title":"Miss","first":"Josefina","last":"Guerrero"},"location":{"street":{"number":7339,"name":"Calle del Prado"},"city":"Ciudad Real","state":"Andalucía","country":"Spain","postcode":12922,"coordinates":{"latitude":"50.3991","longitude":"8.5286"},"timezone":{"offset":"-3:30","description":"Newfoundland"}},"email":"josefina.guerrero@example.com","login":{"uuid":"afa5144c-9245-441c-91c6-39ee225e103a","username":"lazyostrich360","password":"pepper1","salt":"xK4CzGNy","md5":"98e15d012abbf02933154cf2a320d2d4","sha1":"cdbd72031507912f54c26267acec45dc7b134080","sha256":"c630fba5f924de9d970c7ced46ec4f8ae09ead713d2a7dd6649f69ab57e9194c"},"dob":{"date":"1993-09-26T00:25:35.966Z","age":27},"registered":{"date":"2009-11-04T19:04:39.561Z","age":11},"phone":"940-063-636","cell":"654-442-357","id":{"name":"DNI","value":"65894100-S"},"picture":{"large":"https://randomuser.me/api/portraits/women/51.jpg","medium":"https://randomuser.me/api/portraits/med/women/51.jpg","thumbnail":"https://randomuser.me/api/portraits/thumb/women/51.jpg"},"nat":"ES"},{"gender":"male","name":{"title":"Monsieur","first":"Halil","last":"Brunet"},"location":{"street":{"number":6324,"name":"Rue André-Gide"},"city":"St. Margrethen","state":"Schaffhausen","country":"Switzerland","postcode":1684,"coordinates":{"latitude":"45.9026","longitude":"6.7368"},"timezone":{"offset":"+8:00","description":"Beijing, Perth, Singapore, Hong Kong"}},"email":"halil.brunet@example.com","login":{"uuid":"5a8c64b1-425d-4d01-ada1-e35e926ead3f","username":"redpeacock493","password":"rockhard","salt":"yLUZ3L8x","md5":"807f67f1976712555d91577d98240dbe","sha1":"7fb8bde370f5f1e2da632c37f228f1d2fce88308","sha256":"708e31d062b8f1bded074257f757c45ed03fb4fa207a064858c4214603771c30"},"dob":{"date":"1962-12-20T17:32:44.442Z","age":58},"registered":{"date":"2003-01-15T06:39:23.459Z","age":17},"phone":"079 937 13 48","cell":"079 278 34 78","id":{"name":"AVS","value":"756.5763.7994.31"},"picture":{"large":"https://randomuser.me/api/portraits/men/71.jpg","medium":"https://randomuser.me/api/portraits/med/men/71.jpg","thumbnail":"https://randomuser.me/api/portraits/thumb/men/71.jpg"},"nat":"CH"},{"gender":"male","name":{"title":"Mr","first":"Gökhan","last":"Koçoğlu"},"location":{"street":{"number":7680,"name":"Vatan Cd"},"city":"Isparta","state":"Samsun","country":"Turkey","postcode":10926,"coordinates":{"latitude":"-42.5102","longitude":"-114.8811"},"timezone":{"offset":"+4:30","description":"Kabul"}},"email":"gokhan.kocoglu@example.com","login":{"uuid":"f2d4d4fd-394d-4ee5-b3c8-be2583ad6b1d","username":"goldenzebra576","password":"404040","salt":"Bl35KW4p","md5":"b00d34abbd61fcc36c5f891b15d3c782","sha1":"48aa5c18eda44c75918a84c9528784ee7b2967b6","sha256":"f1a2d41f48ba2f26ea1044f1c507b0583c95e16ce3956cd6d36c9ec33e256c3c"},"dob":{"date":"1970-10-22T02:13:38.452Z","age":50},"registered":{"date":"2002-08-27T19:37:24.977Z","age":18},"phone":"(400)-989-2684","cell":"(796)-907-2119","id":{"name":"","value":null},"picture":{"large":"https://randomuser.me/api/portraits/men/10.jpg","medium":"https://randomuser.me/api/portraits/med/men/10.jpg","thumbnail":"https://randomuser.me/api/portraits/thumb/men/10.jpg"},"nat":"TR"},{"gender":"female","name":{"title":"Miss","first":"Teresa","last":"Clark"},"location":{"street":{"number":908,"name":"Valwood Pkwy"},"city":"Brisbane","state":"Australian Capital Territory","country":"Australia","postcode":7921,"coordinates":{"latitude":"77.6816","longitude":"-18.7826"},"timezone":{"offset":"+7:00","description":"Bangkok, Hanoi, Jakarta"}},"email":"teresa.clark@example.com","login":{"uuid":"0233091e-e320-46c5-82b7-aafdcd254686","username":"whiteelephant402","password":"hungry","salt":"48mxXpm7","md5":"1a95d9a874619d8f74e78dd5524228a1","sha1":"fa43060539e765afb581c39dcaba67b2fd272669","sha256":"a19262cd03b1b97943bd27897bac1759ea197091f1a6f19fa04f6c57c89a6f9a"},"dob":{"date":"1996-04-08T15:21:51.254Z","age":24},"registered":{"date":"2008-05-17T13:22:59.038Z","age":12},"phone":"07-2807-1617","cell":"0423-388-864","id":{"name":"TFN","value":"878282403"},"picture":{"large":"https://randomuser.me/api/portraits/women/43.jpg","medium":"https://randomuser.me/api/portraits/med/women/43.jpg","thumbnail":"https://randomuser.me/api/portraits/thumb/women/43.jpg"},"nat":"AU"},{"gender":"male","name":{"title":"Mr","first":"Esat","last":"Arıcan"},"location":{"street":{"number":8478,"name":"Tunalı Hilmi Cd"},"city":"Artvin","state":"Amasya","country":"Turkey","postcode":49365,"coordinates":{"latitude":"26.4031","longitude":"-109.9512"},"timezone":{"offset":"-3:00","description":"Brazil, Buenos Aires, Georgetown"}},"email":"esat.arican@example.com","login":{"uuid":"79a8cb34-f048-4de9-a618-95c8684dc50c","username":"redmeercat789","password":"maradona","salt":"BHeKazpN","md5":"c19d8e6a0a63ffb392b289ed83d26cd0","sha1":"35dc35cd3dd3429ffd023c2aa767183068842349","sha256":"dcb13df9dc77063c669847ebb1e593d58a869b92d516040f4bc973d0ae5efc9e"},"dob":{"date":"1975-09-21T19:33:17.608Z","age":45},"registered":{"date":"2016-03-28T21:50:26.751Z","age":4},"phone":"(896)-846-4348","cell":"(707)-540-4152","id":{"name":"","value":null},"picture":{"large":"https://randomuser.me/api/portraits/men/92.jpg","medium":"https://randomuser.me/api/portraits/med/men/92.jpg","thumbnail":"https://randomuser.me/api/portraits/thumb/men/92.jpg"},"nat":"TR"},{"gender":"male","name":{"title":"Mr","first":"Ricky","last":"Ruiz"},"location":{"street":{"number":2467,"name":"Fairview Road"},"city":"Bath","state":"West Midlands","country":"United Kingdom","postcode":"V95 3NQ","coordinates":{"latitude":"-26.1405","longitude":"-54.7045"},"timezone":{"offset":"-12:00","description":"Eniwetok, Kwajalein"}},"email":"ricky.ruiz@example.com","login":{"uuid":"f2eccd16-4888-411c-a75c-65b8b65b192a","username":"goldenlion113","password":"speaker","salt":"pv6flvfp","md5":"deb384affcdd856faf74feb6fa71bc70","sha1":"4385c32ba644a2b956b2cdbad0c4e1df8aaba1e0","sha256":"4a032d3bab7ad9970a72e69bae215a1c734ddccfa52a6eea5a480f418eb89dd5"},"dob":{"date":"1948-08-22T16:32:36.925Z","age":72},"registered":{"date":"2009-02-20T10:08:45.862Z","age":11},"phone":"017683 26617","cell":"0739-556-278","id":{"name":"NINO","value":"HE 92 29 03 Z"},"picture":{"large":"https://randomuser.me/api/portraits/men/66.jpg","medium":"https://randomuser.me/api/portraits/med/men/66.jpg","thumbnail":"https://randomuser.me/api/portraits/thumb/men/66.jpg"},"nat":"GB"},{"gender":"male","name":{"title":"Mr","first":"Erman","last":"El Morabit"},"location":{"street":{"number":4401,"name":"Burgemeester A Wiedykstraat"},"city":"Moddergat","state":"Gelderland","country":"Netherlands","postcode":17538,"coordinates":{"latitude":"-75.6266","longitude":"146.8196"},"timezone":{"offset":"+9:00","description":"Tokyo, Seoul, Osaka, Sapporo, Yakutsk"}},"email":"erman.elmorabit@example.com","login":{"uuid":"a9d9e017-fc88-46cc-b5c5-6e2a31fb2b50","username":"sadrabbit623","password":"pool","salt":"N4jDa7Cs","md5":"e4a309ea991f3789ed7c34dbb4b1aed2","sha1":"171670f8d47b57be4173b0a9b967e50eb87a1020","sha256":"ff38d18a914782bb5ac9e6f7f58c023010b6e1fedbfc5d0f8902c7051ef635a5"},"dob":{"date":"1966-12-23T01:08:52.592Z","age":54},"registered":{"date":"2002-09-09T08:23:28.011Z","age":18},"phone":"(619)-714-9456","cell":"(027)-689-5919","id":{"name":"BSN","value":"95835049"},"picture":{"large":"https://randomuser.me/api/portraits/men/57.jpg","medium":"https://randomuser.me/api/portraits/med/men/57.jpg","thumbnail":"https://randomuser.me/api/portraits/thumb/men/57.jpg"},"nat":"NL"},{"gender":"female","name":{"title":"Ms","first":"Dorota","last":"Kuntze"},"location":{"street":{"number":3244,"name":"Birkenweg"},"city":"Heringen (Werra)","state":"Hessen","country":"Germany","postcode":91477,"coordinates":{"latitude":"-56.4666","longitude":"160.7358"},"timezone":{"offset":"-2:00","description":"Mid-Atlantic"}},"email":"dorota.kuntze@example.com","login":{"uuid":"5a834376-faac-4d78-97b3-5a23d2526b95","username":"orangebear763","password":"colors","salt":"yErn1Nd2","md5":"fc602c84704afc3f747e789c04135711","sha1":"7e1d6a52ca35dc901e075d7b9e71b12188e51436","sha256":"47a7f4f3ca2e299f6f285da77aea792097363666f4cf2ad6e7c6f0802a81889f"},"dob":{"date":"1971-10-06T16:47:26.280Z","age":49},"registered":{"date":"2007-10-05T19:36:40.048Z","age":13},"phone":"0405-0764808","cell":"0179-3592758","id":{"name":"","value":null},"picture":{"large":"https://randomuser.me/api/portraits/women/18.jpg","medium":"https://randomuser.me/api/portraits/med/women/18.jpg","thumbnail":"https://randomuser.me/api/portraits/thumb/women/18.jpg"},"nat":"DE"},{"gender":"female","name":{"title":"Madame","first":"Lucy","last":"Louis"},"location":{"street":{"number":2319,"name":"Rue Abel-Gance"},"city":"Fläsch","state":"Luzern","country":"Switzerland","postcode":2423,"coordinates":{"latitude":"-7.5324","longitude":"-159.8507"},"timezone":{"offset":"-1:00","description":"Azores, Cape Verde Islands"}},"email":"lucy.louis@example.com","login":{"uuid":"a03f2dd6-e5b3-4864-838f-3170977ea25b","username":"lazypeacock116","password":"michele","salt":"TFf92tzG","md5":"3d8facc1e6a43daa90469dda338f982d","sha1":"8568a3c0a13bd8103daa85a28f00f6ba428bfef6","sha256":"ff30f30dcb31e84ca60c00c8fdbacbcd4c2ec93160282ff306da69eab8826cdd"},"dob":{"date":"1972-11-02T15:25:22.076Z","age":48},"registered":{"date":"2006-08-30T21:19:41.789Z","age":14},"phone":"076 088 76 78","cell":"075 513 25 53","id":{"name":"AVS","value":"756.9758.2488.28"},"picture":{"large":"https://randomuser.me/api/portraits/women/84.jpg","medium":"https://randomuser.me/api/portraits/med/women/84.jpg","thumbnail":"https://randomuser.me/api/portraits/thumb/women/84.jpg"},"nat":"CH"},{"gender":"female","name":{"title":"Ms","first":"Lena","last":"Giraud"},"location":{"street":{"number":607,"name":"Avenue Joliot Curie"},"city":"Asnières-sur-Seine","state":"Ain","country":"France","postcode":13684,"coordinates":{"latitude":"41.4039","longitude":"-10.9072"},"timezone":{"offset":"-10:00","description":"Hawaii"}},"email":"lena.giraud@example.com","login":{"uuid":"55ccc79d-b048-450f-9c42-ab5841da5f0a","username":"heavyleopard969","password":"silvia","salt":"pmkUL7TT","md5":"2084044a11e572561833d5e888607669","sha1":"1f84137c208e51c452565c26e58d6277a2a67d74","sha256":"bda002129d910452c230e915d12fcc5c01cdcbe996708b5df73b1d36076edada"},"dob":{"date":"1980-12-02T19:57:53.340Z","age":40},"registered":{"date":"2007-03-09T18:27:23.955Z","age":13},"phone":"02-26-06-28-65","cell":"06-09-25-58-12","id":{"name":"INSEE","value":"2NNaN75834566 14"},"picture":{"large":"https://randomuser.me/api/portraits/women/82.jpg","medium":"https://randomuser.me/api/portraits/med/women/82.jpg","thumbnail":"https://randomuser.me/api/portraits/thumb/women/82.jpg"},"nat":"FR"},{"gender":"female","name":{"title":"Miss","first":"Kimberly","last":"Porter"},"location":{"street":{"number":6160,"name":"West Street"},"city":"Bristol","state":"Hampshire","country":"United Kingdom","postcode":"VU6S 1PH","coordinates":{"latitude":"30.5836","longitude":"-49.4642"},"timezone":{"offset":"-3:00","description":"Brazil, Buenos Aires, Georgetown"}},"email":"kimberly.porter@example.com","login":{"uuid":"f56152c5-3b33-46e7-9e01-50e01c9a431c","username":"smallduck195","password":"gore","salt":"TKSE4kvn","md5":"8d13cb17b60a8a79aeeab66cb4ea3451","sha1":"f0fe2c0a2632e80242db841f3c8e28d73d0ab090","sha256":"8655bcddab954bd9695e03ac74c14389c3ec4400a64128d9da823c5884852401"},"dob":{"date":"1998-07-28T18:34:26.136Z","age":22},"registered":{"date":"2007-12-23T14:10:56.361Z","age":13},"phone":"013873 29323","cell":"0701-760-697","id":{"name":"NINO","value":"NC 91 76 41 O"},"picture":{"large":"https://randomuser.me/api/portraits/women/62.jpg","medium":"https://randomuser.me/api/portraits/med/women/62.jpg","thumbnail":"https://randomuser.me/api/portraits/thumb/women/62.jpg"},"nat":"GB"},{"gender":"male","name":{"title":"Mr","first":"Judas","last":"Moura"},"location":{"street":{"number":8683,"name":"Rua Dezessete "},"city":"Itapevi","state":"Paraíba","country":"Brazil","postcode":78174,"coordinates":{"latitude":"16.1347","longitude":"-173.1345"},"timezone":{"offset":"0:00","description":"Western Europe Time, London, Lisbon, Casablanca"}},"email":"judas.moura@example.com","login":{"uuid":"ffda7a56-7f03-4cb7-ae3c-31064db76cb1","username":"tinycat136","password":"lincoln","salt":"k7RHa3r9","md5":"4eae3e7290de9c7dc20bb2879664ef0a","sha1":"74d50305dd29a5f688948946170cb427005b239a","sha256":"963f0f4dccfb901d1ef7a0fd31c5d43a68609f86a482c33a48be82f409834e97"},"dob":{"date":"1968-04-26T17:33:43.740Z","age":52},"registered":{"date":"2009-06-21T05:20:03.583Z","age":11},"phone":"(24) 1831-1844","cell":"(19) 1269-8948","id":{"name":"","value":null},"picture":{"large":"https://randomuser.me/api/portraits/men/26.jpg","medium":"https://randomuser.me/api/portraits/med/men/26.jpg","thumbnail":"https://randomuser.me/api/portraits/thumb/men/26.jpg"},"nat":"BR"},{"gender":"female","name":{"title":"Ms","first":"Katrine","last":"Toresen"},"location":{"street":{"number":5948,"name":"Rødbergveien"},"city":"Borkenes","state":"Telemark","country":"Norway","postcode":"6637","coordinates":{"latitude":"33.0819","longitude":"138.3642"},"timezone":{"offset":"+7:00","description":"Bangkok, Hanoi, Jakarta"}},"email":"katrine.toresen@example.com","login":{"uuid":"2ad962e3-827b-497f-9406-91dff2a70e57","username":"whiteladybug520","password":"michael2","salt":"vOOOwqY3","md5":"349597af1bb30df6444c282f67b2b5b5","sha1":"d8b18510ebcbd07201e7637d78818617590564e4","sha256":"a1b032ade6af36ff9fd26ec2cb2b430d57e3162a75553f684f3422703d814610"},"dob":{"date":"1974-06-21T12:52:45.332Z","age":46},"registered":{"date":"2006-09-22T15:45:08.394Z","age":14},"phone":"83521897","cell":"95435155","id":{"name":"FN","value":"21067443281"},"picture":{"large":"https://randomuser.me/api/portraits/women/38.jpg","medium":"https://randomuser.me/api/portraits/med/women/38.jpg","thumbnail":"https://randomuser.me/api/portraits/thumb/women/38.jpg"},"nat":"NO"},{"gender":"female","name":{"title":"Miss","first":"Nalan","last":"Yeşilkaya"},"location":{"street":{"number":2160,"name":"Atatürk Sk"},"city":"Antalya","state":"Çanakkale","country":"Turkey","postcode":27783,"coordinates":{"latitude":"-40.3387","longitude":"-169.7726"},"timezone":{"offset":"-11:00","description":"Midway Island, Samoa"}},"email":"nalan.yesilkaya@example.com","login":{"uuid":"5911ced4-adf0-44ae-9492-b4748c44beb4","username":"ticklishlion935","password":"modles","salt":"XwaHYUcE","md5":"6f5f414762cdd6e249f33db45e2c8a00","sha1":"1b76d0ea404d14f03e9ba14a7dc7998eed484d18","sha256":"c94e184c6c5a34aaa861c28d8f693d2aff0e16da4621270751915fdc19603bbd"},"dob":{"date":"1966-12-08T16:24:02.792Z","age":54},"registered":{"date":"2008-08-25T19:18:34.968Z","age":12},"phone":"(741)-984-6416","cell":"(257)-797-8540","id":{"name":"","value":null},"picture":{"large":"https://randomuser.me/api/portraits/women/1.jpg","medium":"https://randomuser.me/api/portraits/med/women/1.jpg","thumbnail":"https://randomuser.me/api/portraits/thumb/women/1.jpg"},"nat":"TR"},{"gender":"male","name":{"title":"Mr","first":"Isaac","last":"Hughes"},"location":{"street":{"number":8792,"name":"East Tamaki Road"},"city":"Timaru","state":"Waikato","country":"New Zealand","postcode":48303,"coordinates":{"latitude":"-23.3328","longitude":"170.7936"},"timezone":{"offset":"-8:00","description":"Pacific Time (US & Canada)"}},"email":"isaac.hughes@example.com","login":{"uuid":"a6c8771c-c41d-47aa-8034-52354f200400","username":"heavyfish741","password":"doggy","salt":"diP4aLGc","md5":"0b7f997f8d37c05ee4ba9e3d60c0201a","sha1":"591ccb85820be2f5db636c7e5764486d81bd8ebd","sha256":"cee59ec8485953a91a02fcdc8a5017ef08e0254798fabd05fb5b46c4ec6c3c17"},"dob":{"date":"1969-12-06T00:45:14.619Z","age":51},"registered":{"date":"2004-06-19T19:26:18.413Z","age":16},"phone":"(542)-181-7902","cell":"(041)-180-0484","id":{"name":"","value":null},"picture":{"large":"https://randomuser.me/api/portraits/men/42.jpg","medium":"https://randomuser.me/api/portraits/med/men/42.jpg","thumbnail":"https://randomuser.me/api/portraits/thumb/men/42.jpg"},"nat":"NZ"},{"gender":"female","name":{"title":"Mrs","first":"Violet","last":"Jackson"},"location":{"street":{"number":6435,"name":"High Street"},"city":"Whangarei","state":"West Coast","country":"New Zealand","postcode":87615,"coordinates":{"latitude":"63.9487","longitude":"-141.8043"},"timezone":{"offset":"-3:30","description":"Newfoundland"}},"email":"violet.jackson@example.com","login":{"uuid":"7242b1ac-8beb-4c1d-ba7e-635c4486400d","username":"smallduck155","password":"aptiva","salt":"JWZ1gZ3K","md5":"e788649dd30f5ce98c597cb1cb95a31d","sha1":"4c696b1a12a76ed4ac55b5e64ff017f322e102d8","sha256":"e7faaf39bf585e1abd650b273a8dfa7961f0c0f4608155cb65e8013d1f180db6"},"dob":{"date":"1994-08-12T16:42:21.210Z","age":26},"registered":{"date":"2007-11-15T03:26:55.126Z","age":13},"phone":"(342)-288-6190","cell":"(445)-086-8641","id":{"name":"","value":null},"picture":{"large":"https://randomuser.me/api/portraits/women/50.jpg","medium":"https://randomuser.me/api/portraits/med/women/50.jpg","thumbnail":"https://randomuser.me/api/portraits/thumb/women/50.jpg"},"nat":"NZ"},{"gender":"male","name":{"title":"Mr","first":"August","last":"Larsen"},"location":{"street":{"number":9010,"name":"Orionvej"},"city":"København S","state":"Nordjylland","country":"Denmark","postcode":70639,"coordinates":{"latitude":"-87.6501","longitude":"-173.6333"},"timezone":{"offset":"+7:00","description":"Bangkok, Hanoi, Jakarta"}},"email":"august.larsen@example.com","login":{"uuid":"79c2f93c-efc1-4fcc-ae39-4138b77cf6a4","username":"tinypeacock117","password":"babies","salt":"HoAFjHq0","md5":"30f21185d152dad77d506fc40bf916a5","sha1":"cf958f0c2cc87ee97ba4898d552b31655541a5f6","sha256":"c3f09111b5a59cf25017fd54db138922b8af9c8509850cb4d5a2b828b33061f6"},"dob":{"date":"1953-10-17T09:15:29.667Z","age":67},"registered":{"date":"2004-02-03T14:21:41.976Z","age":16},"phone":"83928185","cell":"68927963","id":{"name":"CPR","value":"171053-6412"},"picture":{"large":"https://randomuser.me/api/portraits/men/66.jpg","medium":"https://randomuser.me/api/portraits/med/men/66.jpg","thumbnail":"https://randomuser.me/api/portraits/thumb/men/66.jpg"},"nat":"DK"},{"gender":"male","name":{"title":"Mr","first":"Randolfo","last":"Cardoso"},"location":{"street":{"number":7215,"name":"Rua Principal"},"city":"Caucaia","state":"Mato Grosso","country":"Brazil","postcode":27150,"coordinates":{"latitude":"-46.4380","longitude":"151.9055"},"timezone":{"offset":"-6:00","description":"Central Time (US & Canada), Mexico City"}},"email":"randolfo.cardoso@example.com","login":{"uuid":"178482a1-8976-4219-9a12-f1039998ed52","username":"purplemouse166","password":"raiders1","salt":"JDQq2kf4","md5":"c5f1944377375f0c8932a119ddebc6d4","sha1":"80ba8286fff667c0bf0ec6f3c623e427d89a5900","sha256":"e76780ff75ee5f37fefc5ae17aa072885d43f730c953db09684f519bca990e77"},"dob":{"date":"1983-08-29T00:51:36.639Z","age":37},"registered":{"date":"2015-10-15T09:58:48.655Z","age":5},"phone":"(92) 8275-1270","cell":"(12) 1687-5993","id":{"name":"","value":null},"picture":{"large":"https://randomuser.me/api/portraits/men/86.jpg","medium":"https://randomuser.me/api/portraits/med/men/86.jpg","thumbnail":"https://randomuser.me/api/portraits/thumb/men/86.jpg"},"nat":"BR"}],"info":{"seed":"6948cb1adcf90203","results":50,"page":1,"version":"1.3"}}